notionalpha/__init__.py
notionalpha/client.py
notionalpha/signal_analyzer.py
notionalpha/types.py
notionalpha/providers/__init__.py
notionalpha/providers/anthropic.py
notionalpha/providers/azure_openai.py
notionalpha/providers/openai.py
notionalpha_clarity-0.2.0.dist-info/METADATA
notionalpha_clarity-0.2.0.dist-info/WHEEL
notionalpha_clarity-0.2.0.dist-info/top_level.txt
notionalpha_clarity-0.2.0.dist-info/RECORD
