Metadata-Version: 2.4
Name: notionalpha-clarity
Version: 0.2.0
Summary: Python SDK for NotionAlpha Clarity - AI Value Realization Platform
Author-email: NotionAlpha <support@notionalpha.com>
License: MIT
Project-URL: Homepage, https://notionalpha.com
Project-URL: Documentation, https://docs.notionalpha.com
Project-URL: Repository, https://github.com/NotionAlpha/notionalpha
Project-URL: Issues, https://github.com/NotionAlpha/notionalpha/issues
Keywords: notionalpha,clarity,ai,llm,finops,value-realization,roi,openai,anthropic,azure
Classifier: Development Status :: 3 - Alpha
Classifier: Intended Audience :: Developers
Classifier: License :: OSI Approved :: MIT License
Classifier: Programming Language :: Python :: 3
Classifier: Programming Language :: Python :: 3.8
Classifier: Programming Language :: Python :: 3.9
Classifier: Programming Language :: Python :: 3.10
Classifier: Programming Language :: Python :: 3.11
Classifier: Programming Language :: Python :: 3.12
Requires-Python: >=3.8
Requires-Dist: requests>=2.31.0
Requires-Dist: typing-extensions>=4.0.0
Provides-Extra: openai
Requires-Dist: openai>=1.0.0; extra == "openai"
Provides-Extra: anthropic
Requires-Dist: anthropic>=0.20.0; extra == "anthropic"
Provides-Extra: all
Requires-Dist: openai>=1.0.0; extra == "all"
Requires-Dist: anthropic>=0.20.0; extra == "all"
Provides-Extra: dev
Requires-Dist: pytest>=7.0.0; extra == "dev"
Requires-Dist: pytest-asyncio>=0.21.0; extra == "dev"
Requires-Dist: black>=23.0.0; extra == "dev"
Requires-Dist: mypy>=1.0.0; extra == "dev"
Requires-Dist: ruff>=0.1.0; extra == "dev"
